dynodb.py
dynodb-0.3.0.dist-info/METADATA
dynodb-0.3.0.dist-info/WHEEL
dynodb-0.3.0.dist-info/entry_points.txt
dynodb-0.3.0.dist-info/top_level.txt
dynodb-0.3.0.dist-info/RECORD
