Metadata-Version: 2.1
Name: dynodb
Version: 0.3.0
Requires-Dist: requests
Requires-Dist: argparse
